{"skeleton":{"hash":"UYljWdR4BLewlkGCuD6uf1xwsqM","spine":"2.1.27","width":547,"height":688},"bones":[{"name":"root"},{"name":"step1","parent":"root"},{"name":"step2","parent":"root"},{"name":"flame","parent":"step2","x":-152.49,"scaleX":0.63,"scaleY":0.83,"rotation":270},{"name":"frame","parent":"step1"},{"name":"frame2","parent":"step2"},{"name":"green-dot","parent":"step2","x":223.31},{"name":"green-illum","parent":"step2","x":-54.02},{"name":"man1","parent":"step1","x":-233,"y":-173.25},{"name":"man2","parent":"step1","x":-232.64,"y":-173.25},{"name":"man3","parent":"step1","x":233.64,"y":-173.24,"scaleX":-1},{"name":"man4","parent":"step1","x":232.64,"y":-173.24},{"name":"red-dot","parent":"step2","x":223.32},{"name":"rocket","parent":"step1"},{"name":"rocket2","parent":"step2","x":-69.94},{"name":"score","parent":"step2","x":-52.31,"y":53.19},{"name":"slide","parent":"step2","x":112.05,"y":173.41,"scaleX":6.762,"scaleY":0.439}],"slots":[{"name":"step1/frame","bone":"frame","attachment":"step1/frame"},{"name":"step1/rocket1","bone":"rocket","attachment":"step1/rocket1"},{"name":"step1/man","bone":"man1","attachment":"step1/man1"},{"name":"step1/man2","bone":"man2","attachment":"step1/man2"},{"name":"step1/man3","bone":"man3","attachment":"step1/man3"},{"name":"step1/man4","bone":"man4","attachment":"step1/man4"},{"name":"step2/frame2","bone":"frame2","attachment":"step2/frame2"},{"name":"step2/green-dot","bone":"green-dot","attachment":"step2/green-dot"},{"name":"step2/red-dot","bone":"red-dot","attachment":"step2/red-dot"},{"name":"step2/flame","bone":"flame","attachment":"step2/flame"},{"name":"step2/rocket2","bone":"rocket2","attachment":"step2/rocket2"},{"name":"step2/score","bone":"score","attachment":"step2/score"},{"name":"step2/green-ilumination","bone":"green-illum","attachment":"step2/green-ilumination"},{"name":"step2/slide","bone":"slide","attachment":"step2/slide"}],"skins":{"default":{"step1/frame":{"step1/frame":{"width":547,"height":688}},"step1/man":{"step1/man1":{"width":29,"height":51}},"step1/man2":{"step1/man2":{"width":29,"height":51}},"step1/man3":{"step1/man3":{"width":29,"height":51}},"step1/man4":{"step1/man4":{"scaleX":-1,"width":29,"height":51}},"step1/rocket1":{"step1/rocket1":{"y":-44.6,"width":169,"height":308}},"step2/flame":{"step2/flame":{"width":41,"height":51}},"step2/frame2":{"step2/frame2":{"width":547,"height":688}},"step2/green-dot":{"step2/green-dot":{"width":54,"height":54}},"step2/green-ilumination":{"step2/green-ilumination":{"width":23,"height":23}},"step2/red-dot":{"step2/red-dot":{"width":54,"height":54}},"step2/rocket2":{"step2/rocket2":{"width":162,"height":90}},"step2/score":{"step2/score":{"width":49,"height":46}},"step2/slide":{"step2/slide":{"width":10,"height":10}}}},"events":{"step1-load":{},"step2-click":{}},"animations":{"step1":{"slots":{"step1/man":{"color":[{"time":0,"color":"ffffffff","curve":"stepped"},{"time":0.2,"color":"ffffffff"},{"time":0.2333,"color":"ffffff00"}]},"step1/man2":{"color":[{"time":0,"color":"ffffff00","curve":"stepped"},{"time":0.0666,"color":"ffffff00"},{"time":0.1,"color":"ffffffff","curve":"stepped"},{"time":0.4333,"color":"ffffffff"},{"time":0.4666,"color":"ffffff00"}]},"step1/man3":{"color":[{"time":0,"color":"ffffff00","curve":"stepped"},{"time":0.1,"color":"ffffff00"},{"time":0.1333,"color":"ffffffff","curve":"stepped"},{"time":0.2666,"color":"ffffffff"},{"time":0.3,"color":"ffffff00"}]},"step1/man4":{"color":[{"time":0,"color":"ffffff00","curve":"stepped"},{"time":0.2,"color":"ffffff00"},{"time":0.2333,"color":"ffffffff","curve":"stepped"},{"time":0.5,"color":"ffffffff","curve":"stepped"},{"time":0.5333,"color":"ffffffff"},{"time":0.5666,"color":"ffffff00"}]},"step2/flame":{"color":[{"time":0,"color":"ffffff00"}]},"step2/frame2":{"color":[{"time":0,"color":"ffffff00"}]},"step2/green-dot":{"color":[{"time":0,"color":"ffffff00"}]},"step2/green-ilumination":{"color":[{"time":0,"color":"ffffff00"}]},"step2/red-dot":{"color":[{"time":0,"color":"ffffff00"}]},"step2/rocket2":{"color":[{"time":0,"color":"ffffff00"}]},"step2/score":{"color":[{"time":0,"color":"ffffff00"}]},"step2/slide":{"color":[{"time":0,"color":"ffffff00"}]}},"bones":{"rocket":{"translate":[{"time":0.2,"x":0,"y":0},{"time":0.2333,"x":0,"y":15.14},{"time":0.2666,"x":0,"y":0},{"time":0.3,"x":0,"y":15.14},{"time":0.3333,"x":0,"y":0,"curve":"stepped"},{"time":0.4333,"x":0,"y":0},{"time":0.4666,"x":0,"y":15.14},{"time":0.5,"x":0,"y":0,"curve":"stepped"},{"time":0.5333,"x":0,"y":0},{"time":0.5666,"x":0,"y":15.14},{"time":0.6,"x":0,"y":0}],"scale":[{"time":0.2,"x":1,"y":1},{"time":0.2333,"x":1.049,"y":1.069},{"time":0.2666,"x":1,"y":1},{"time":0.3,"x":1.049,"y":1.069},{"time":0.3333,"x":1,"y":1,"curve":"stepped"},{"time":0.4333,"x":1,"y":1},{"time":0.4666,"x":1.049,"y":1.069},{"time":0.5,"x":1,"y":1,"curve":"stepped"},{"time":0.5333,"x":1,"y":1},{"time":0.5666,"x":1.049,"y":1.069},{"time":0.6,"x":1,"y":1}]},"man1":{"translate":[{"time":0,"x":0,"y":0},{"time":0.2333,"x":232.51,"y":0},{"time":0.2666,"x":0,"y":0}]},"man2":{"translate":[{"time":0.1,"x":0,"y":0},{"time":0.2,"x":90.3,"y":0},{"time":0.4666,"x":231.47,"y":0},{"time":0.5,"x":0,"y":0}]},"man3":{"translate":[{"time":0.1333,"x":0,"y":0},{"time":0.2,"x":-112.1,"y":0},{"time":0.3,"x":-234.58,"y":0},{"time":0.3333,"x":0,"y":0}]},"man4":{"translate":[{"time":0.2333,"x":0,"y":0},{"time":0.4,"x":-93.41,"y":0},{"time":0.5666,"x":-234.58,"y":0},{"time":0.6,"x":0,"y":0}]}},"events":[{"time":0.2333,"name":"step1-load"},{"time":0.3,"name":"step1-load"},{"time":0.4666,"name":"step1-load"},{"time":0.5666,"name":"step1-load"}]},"step2":{"slots":{"step1/frame":{"color":[{"time":0,"color":"ffffff00"}]},"step1/man":{"attachment":[{"time":0,"name":"step1/man1"}],"color":[{"time":0,"color":"ffffff00"}]},"step1/man2":{"attachment":[{"time":0,"name":"step1/man2"}],"color":[{"time":0,"color":"ffffff00"}]},"step1/man3":{"attachment":[{"time":0,"name":"step1/man3"}],"color":[{"time":0,"color":"ffffff00"}]},"step1/man4":{"attachment":[{"time":0,"name":"step1/man4"}],"color":[{"time":0,"color":"ffffff00"}]},"step1/rocket1":{"attachment":[{"time":0,"name":"step1/rocket1"}],"color":[{"time":0,"color":"ffffff00"}]},"step2/green-dot":{"color":[{"time":0,"color":"ffffff00"},{"time":0.0333,"color":"ffffffff","curve":"stepped"},{"time":0.4,"color":"ffffffff"},{"time":0.4333,"color":"ffffff00"}]},"step2/green-ilumination":{"color":[{"time":0,"color":"ffffff00","curve":"stepped"},{"time":0.2333,"color":"ffffff00"},{"time":0.2666,"color":"ffffffff"},{"time":0.3,"color":"ffffff00"}]},"step2/red-dot":{"color":[{"time":0,"color":"ffffff00","curve":"stepped"},{"time":0.4,"color":"ffffff00"},{"time":0.4333,"color":"ffffffff"}]},"step2/score":{"color":[{"time":0,"color":"ffffff00","curve":"stepped"},{"time":0.2333,"color":"ffffff00"},{"time":0.2666,"color":"ffffffff","curve":"stepped"},{"time":0.3333,"color":"ffffffff"},{"time":0.4,"color":"ffffff00"}]},"step2/slide":{"color":[{"time":0,"color":"ffffffff","curve":"stepped"},{"time":0.1,"color":"ffffffff"},{"time":0.1333,"color":"ffffff00","curve":"stepped"},{"time":0.1666,"color":"ffffff00"},{"time":0.2,"color":"ffffffff","curve":"stepped"},{"time":0.3333,"color":"ffffffff"},{"time":0.3666,"color":"ffffff00","curve":"stepped"},{"time":0.4,"color":"ffffff00"},{"time":0.4333,"color":"ffffffff","curve":"stepped"},{"time":0.5,"color":"ffffffff"},{"time":0.5333,"color":"ffffff00","curve":"stepped"},{"time":0.5666,"color":"ffffff00"},{"time":0.6,"color":"ffffffff","curve":"stepped"},{"time":0.6666,"color":"ffffffff"},{"time":0.7,"color":"ffffff00","curve":"stepped"},{"time":0.7333,"color":"ffffff00"}]}},"bones":{"red-dot":{"translate":[{"time":0,"x":0,"y":0,"curve":"stepped"},{"time":0.4,"x":0,"y":0,"curve":"stepped"},{"time":0.4333,"x":0,"y":0},{"time":0.8,"x":-444.67,"y":0}]},"green-dot":{"translate":[{"time":0,"x":0,"y":0,"curve":"stepped"},{"time":0.0333,"x":0,"y":0},{"time":0.4,"x":-444.67,"y":0,"curve":"stepped"},{"time":0.4333,"x":-444.67,"y":0},{"time":0.4666,"x":0,"y":0}]},"score":{"translate":[{"time":0.2666,"x":0,"y":0},{"time":0.4,"x":0,"y":57.45}]},"slide":{"translate":[{"time":0,"x":81.37,"y":0},{"time":0.1333,"x":-319.88,"y":0},{"time":0.1666,"x":85.58,"y":-354.95},{"time":0.3666,"x":-321.28,"y":-354.95},{"time":0.4,"x":82.09,"y":-78.05},{"time":0.5333,"x":-316.3,"y":-78.05},{"time":0.5666,"x":95.37,"y":-449.89},{"time":0.7,"x":-319.62,"y":-449.89},{"time":0.7333,"x":80.43,"y":119.48}]},"flame":{"scale":[{"time":0,"x":1,"y":1},{"time":0.0666,"x":0.861,"y":1.452},{"time":0.1,"x":1,"y":1},{"time":0.1666,"x":0.861,"y":1.452},{"time":0.2,"x":1,"y":1},{"time":0.2666,"x":0.861,"y":1.452},{"time":0.3,"x":1,"y":1},{"time":0.3666,"x":0.861,"y":1.452},{"time":0.4,"x":1,"y":1},{"time":0.4666,"x":0.861,"y":1.452},{"time":0.5,"x":1,"y":1},{"time":0.5666,"x":0.861,"y":1.452},{"time":0.6,"x":1,"y":1},{"time":0.6666,"x":0.861,"y":1.452},{"time":0.7,"x":1,"y":1},{"time":0.7666,"x":0.861,"y":1.452}]}},"events":[{"time":0.2666,"name":"step2-click"}]}}}